Workbook

Sheet 00_Sommaire
A1: ÉTAPE 2 - ANALYSE DES COÛTS ET DE LA RENTABILITÉ - CHHS
A3: Centre hospitalier horizon SANTÉ (CHHS) - Exercice N
A4: Données fictives construites à des fins pédagogiques et professionnelles.
A6: Onglet | B6: Contenu
A7: 01_Cles_Repartition | B7: Pools de coûts N (issus de l'Étape 1) et clés de répartition par activité
A8: 02_Couts_Rentabilite | B8: Volume, CA, coûts directs/indirects, coût unitaire, marge et taux de marge par activité
A9: 03_Controle_Coherence | B9: Vérification que le total des CA et des coûts par activité reconstitue les totaux de l'Étape 1
A11: Convention de couleur
A12: Bleu = donnée saisie (volume, CA, clé de répartition)
A13: Noir = formule calculée automatiquement
A14: Règle de cohérence : le CA total et le total des coûts par activité doivent être strictement égaux aux montants du compte de résultat de l'Étape 1 (42 500 k€ de CA et 40 674 k€ de charges d'exploitation en N).

Sheet 01_Cles_Repartition
A1: POOLS DE COÛTS N (en k€) - issus de l'Étape 1 (Compte de résultat)
A3: Achats consommés (100% direct) | B3: 6588
A4: Charges de personnel - part directe (75%) | B4: 19604
A5: Charges de personnel - part indirecte (25%, fonctions support) | B5: 6535
A6: Charges externes (100% indirect) | B6: 4888
A7: Impôts et taxes (100% indirect) | B7: 850
A8: Dotations aux amortissements - part directe (60%, équipements médicaux) | B8: 1326
A9: Dotations aux amortissements - part indirecte (40%, bâtiments) | B9: 883
A11: TOTAL POOL COÛTS DIRECTS | B11: =B3+B4+B8 -> 27518
A12: TOTAL POOL COÛTS INDIRECTS | B12: =B5+B6+B7+B9 -> 13156
A15: CLÉS DE RÉPARTITION PAR ACTIVITÉ
A17: Activité | B17: Poids Achats (clé : nature de consommation) | C17: Poids Personnel direct (clé : ETP affectés) | D17: Poids Amortissements directs (clé : équipement médical dédié) | E17: Poids coûts indirects (clé : ETP affectés)
A18: Consultations externes | B18: 0.03 | C18: 0.15 | D18: 0.03 | E18: 0.15
A19: Hospitalisation complète | B19: 0.3 | C19: 0.4 | D19: 0.08 | E19: 0.4
A20: Hospitalisation de jour | B20: 0.1 | C20: 0.1 | D20: 0.04 | E20: 0.1
A21: Bloc opératoire | B21: 0.35 | C21: 0.22 | D21: 0.3 | E21: 0.22
A22: Imagerie médicale | B22: 0.07 | C22: 0.08 | D22: 0.4 | E22: 0.08
A23: Laboratoire | B23: 0.15 | C23: 0.05 | D23: 0.15 | E23: 0.05
A24: Contrôle : somme des poids (doit être 100%) | B24: =SUM(B18:B23) -> 1 | C24: =SUM(C18:C23) -> 1 | D24: =SUM(D18:D23) -> 1 | E24: =SUM(E18:E23) -> 1

Sheet 02_Couts_Rentabilite
A1: COÛTS ET RENTABILITÉ PAR ACTIVITÉ - CHHS - EXERCICE N (en k€ sauf mention contraire)
A3: Activité | B3: Volume | C3: CA (k€) | D3: Achats directs | E3: Personnel direct | F3: Amort. direct | G3: Total coûts directs | H3: Coûts indirects | I3: Total coût | J3: Coût unitaire (€) | K3: Marge (k€) | L3: Taux de marge
A4: Consultations externes | B4: 85000 | C4: 6375 | D4: ='01_Cles_Repartition'!B18*'01_Cles_Repartition'!$B$3 -> 197.64 | E4: ='01_Cles_Repartition'!C18*'01_Cles_Repartition'!$B$4 -> 2940.6 | F4: ='01_Cles_Repartition'!D18*'01_Cles_Repartition'!$B$8 -> 39.78 | G4: =SUM(D4:F4) -> 3178.02 | H4: ='01_Cles_Repartition'!E18*'01_Cles_Repartition'!$B$12 -> 1973.4 | I4: =G4+H4 -> 5151.42 | J4: =IFERROR(I4*1000/B4,"-") -> 60.604941 | K4: =C4-I4 -> 1223.58 | L4: =IFERROR(K4/C4,"-") -> 0.19193412
A5: Hospitalisation complète | B5: 4200 | C5: 17000 | D5: ='01_Cles_Repartition'!B19*'01_Cles_Repartition'!$B$3 -> 1976.4 | E5: ='01_Cles_Repartition'!C19*'01_Cles_Repartition'!$B$4 -> 7841.6 | F5: ='01_Cles_Repartition'!D19*'01_Cles_Repartition'!$B$8 -> 106.08 | G5: =SUM(D5:F5) -> 9924.08 | H5: ='01_Cles_Repartition'!E19*'01_Cles_Repartition'!$B$12 -> 5262.4 | I5: =G5+H5 -> 15186.48 | J5: =IFERROR(I5*1000/B5,"-") -> 3615.8286 | K5: =C5-I5 -> 1813.52 | L5: =IFERROR(K5/C5,"-") -> 0.10667765
A6: Hospitalisation de jour | B6: 6800 | C6: 5100 | D6: ='01_Cles_Repartition'!B20*'01_Cles_Repartition'!$B$3 -> 658.8 | E6: ='01_Cles_Repartition'!C20*'01_Cles_Repartition'!$B$4 -> 1960.4 | F6: ='01_Cles_Repartition'!D20*'01_Cles_Repartition'!$B$8 -> 53.04 | G6: =SUM(D6:F6) -> 2672.24 | H6: ='01_Cles_Repartition'!E20*'01_Cles_Repartition'!$B$12 -> 1315.6 | I6: =G6+H6 -> 3987.84 | J6: =IFERROR(I6*1000/B6,"-") -> 586.44706 | K6: =C6-I6 -> 1112.16 | L6: =IFERROR(K6/C6,"-") -> 0.21807059
A7: Bloc opératoire | B7: 3100 | C7: 7650 | D7: ='01_Cles_Repartition'!B21*'01_Cles_Repartition'!$B$3 -> 2305.8 | E7: ='01_Cles_Repartition'!C21*'01_Cles_Repartition'!$B$4 -> 4312.88 | F7: ='01_Cles_Repartition'!D21*'01_Cles_Repartition'!$B$8 -> 397.8 | G7: =SUM(D7:F7) -> 7016.48 | H7: ='01_Cles_Repartition'!E21*'01_Cles_Repartition'!$B$12 -> 2894.32 | I7: =G7+H7 -> 9910.8 | J7: =IFERROR(I7*1000/B7,"-") -> 3197.0323 | K7: =C7-I7 -> -2260.8 | L7: =IFERROR(K7/C7,"-") -> -0.29552941
A8: Imagerie médicale | B8: 22000 | C8: 4250 | D8: ='01_Cles_Repartition'!B22*'01_Cles_Repartition'!$B$3 -> 461.16 | E8: ='01_Cles_Repartition'!C22*'01_Cles_Repartition'!$B$4 -> 1568.32 | F8: ='01_Cles_Repartition'!D22*'01_Cles_Repartition'!$B$8 -> 530.4 | G8: =SUM(D8:F8) -> 2559.88 | H8: ='01_Cles_Repartition'!E22*'01_Cles_Repartition'!$B$12 -> 1052.48 | I8: =G8+H8 -> 3612.36 | J8: =IFERROR(I8*1000/B8,"-") -> 164.19818 | K8: =C8-I8 -> 637.64 | L8: =IFERROR(K8/C8,"-") -> 0.15003294
A9: Laboratoire | B9: 95000 | C9: 2125 | D9: ='01_Cles_Repartition'!B23*'01_Cles_Repartition'!$B$3 -> 988.2 | E9: ='01_Cles_Repartition'!C23*'01_Cles_Repartition'!$B$4 -> 980.2 | F9: ='01_Cles_Repartition'!D23*'01_Cles_Repartition'!$B$8 -> 198.9 | G9: =SUM(D9:F9) -> 2167.3 | H9: ='01_Cles_Repartition'!E23*'01_Cles_Repartition'!$B$12 -> 657.8 | I9: =G9+H9 -> 2825.1 | J9: =IFERROR(I9*1000/B9,"-") -> 29.737895 | K9: =C9-I9 -> -700.1 | L9: =IFERROR(K9/C9,"-") -> -0.32945882
A10: TOTAL CHHS | B10: =SUM(B4:B9) -> 216100 | C10: =SUM(C4:C9) -> 42500 | D10: =SUM(D4:D9) -> 6588 | E10: =SUM(E4:E9) -> 19604 | F10: =SUM(F4:F9) -> 1326 | G10: =SUM(G4:G9) -> 27518 | H10: =SUM(H4:H9) -> 13156 | I10: =SUM(I4:I9) -> 40674 | K10: =SUM(K4:K9) -> 1826 | L10: =K10/C10 -> 0.042964706

Sheet 03_Controle_Coherence
A1: CONTRÔLE DE COHÉRENCE AVEC L'ÉTAPE 1
A3: Indicateur | B3: Étape 1 (référence) | C3: Étape 2 (recalculé) | D3: Écart
A4: Chiffre d'affaires total N (k€) | B4: 42500 | C4: ='02_Couts_Rentabilite'!C10 -> 42500 | D4: =C4-B4 -> 0
A5: Total charges d'exploitation N (k€) | B5: 40674 | C5: ='02_Couts_Rentabilite'!I10 -> 40674 | D5: =C5-B5 -> 0
A6: Résultat d'exploitation N (k€) | B6: 1826 | C6: ='02_Couts_Rentabilite'!K10 -> 1826 | D6: =C6-B6 -> 0
A9: Un écart non nul signale une rupture de la règle de source unique de données (Section 6 du prompt maître) et doit être corrigé avant diffusion.
