Workbook

Sheet 00_Sommaire
A1: ÉTAPE 7 - PRÉVISIONS N+1 ET SCÉNARIOS - CHHS
A3: Centre hospitalier horizon SANTÉ (CHHS)
A4: Données fictives construites à des fins pédagogiques et professionnelles. Les prévisions sont des estimations basées sur des hypothèses, non des résultats réels.
A6: Onglet | B6: Contenu
A7: 01_Hypotheses_Scenarios | B7: Hypothèses de croissance et de structure de coûts pour les 3 scénarios N+1
A8: 02_Previsions_N1 | B8: Compte de résultat prévisionnel N+1 et trésorerie estimée par scénario
A9: 03_Sensibilite | B9: Analyse de sensibilité du résultat N+1 (scénario central) à chaque hypothèse

Sheet 01_Hypotheses_Scenarios
A1: HYPOTHÈSES PAR SCÉNARIO - EXERCICE N+1
A3: Hypothèse | B3: Prudent | C3: Central | D3: Optimiste
A4: Croissance du CA | B4: 0.01 | C4: 0.035 | D4: 0.06
A5: Masse salariale / CA | B5: 0.63 | C5: 0.615 | D5: 0.6
A6: Achats / CA | B6: 0.158 | C6: 0.153 | D6: 0.15
A7: Charges externes / CA | B7: 0.115 | C7: 0.113 | D7: 0.11
A8: Impôts et taxes / CA | B8: 0.02 | C8: 0.02 | D8: 0.02
A9: Amortissements / CA | B9: 0.053 | C9: 0.052 | D9: 0.05
A10: Résultat financier (k€) | B10: -260 | C10: -240 | D10: -200
A11: Taux d'IS | B11: 0.25 | C11: 0.25 | D11: 0.25
A12: Investissements estimés (k€) | B12: 2500 | C12: 2500 | D12: 2500
A13: Variation du BFR estimée (k€) | B13: 800 | C13: 500 | D13: 200
A16: Rappel N (réalisé, Étape 1) : CA 42 500 k€, taux de marge d'exploitation 4,3 %, résultat net = 1 220 k€, trésorerie 2 100 k€.

Sheet 02_Previsions_N1
A1: COMPTE DE RÉSULTAT PRÉVISIONNEL N+1 PAR SCÉNARIO (en k€)
A3: Indicateur | B3: Prudent | C3: Central | D3: Optimiste
A4: Chiffre d'affaires N+1 | B4: =42500*(1+'01_Hypotheses_Scenarios'!B4) -> 42925 | C4: =42500*(1+'01_Hypotheses_Scenarios'!C4) -> 43987.5 | D4: =42500*(1+'01_Hypotheses_Scenarios'!D4) -> 45050
A5: Charges de personnel | B5: =B4*'01_Hypotheses_Scenarios'!B5 -> 27042.75 | C5: =C4*'01_Hypotheses_Scenarios'!C5 -> 27052.312 | D5: =D4*'01_Hypotheses_Scenarios'!D5 -> 27030
A6: Achats consommés | B6: =B4*'01_Hypotheses_Scenarios'!B6 -> 6782.15 | C6: =C4*'01_Hypotheses_Scenarios'!C6 -> 6730.0875 | D6: =D4*'01_Hypotheses_Scenarios'!D6 -> 6757.5
A7: Charges externes | B7: =B4*'01_Hypotheses_Scenarios'!B7 -> 4936.375 | C7: =C4*'01_Hypotheses_Scenarios'!C7 -> 4970.5875 | D7: =D4*'01_Hypotheses_Scenarios'!D7 -> 4955.5
A8: Impôts et taxes | B8: =B4*'01_Hypotheses_Scenarios'!B8 -> 858.5 | C8: =C4*'01_Hypotheses_Scenarios'!C8 -> 879.75 | D8: =D4*'01_Hypotheses_Scenarios'!D8 -> 901
A9: Dotations aux amortissements | B9: =B4*'01_Hypotheses_Scenarios'!B9 -> 2275.025 | C9: =C4*'01_Hypotheses_Scenarios'!C9 -> 2287.35 | D9: =D4*'01_Hypotheses_Scenarios'!D9 -> 2252.5
A10: Total charges d'exploitation | B10: =SUM(B5:B9) -> 41894.8 | C10: =SUM(C5:C9) -> 41920.088 | D10: =SUM(D5:D9) -> 41896.5
A11: Résultat d'exploitation | B11: =B4-B10 -> 1030.2 | C11: =C4-C10 -> 2067.4125 | D11: =D4-D10 -> 3153.5
A12: Taux de marge d'exploitation | B12: =B11/B4 -> 0.024 | C12: =C11/C4 -> 0.047 | D12: =D11/D4 -> 0.07
A13: Résultat financier | B13: ='01_Hypotheses_Scenarios'!B10 -> -260 | C13: ='01_Hypotheses_Scenarios'!C10 -> -240 | D13: ='01_Hypotheses_Scenarios'!D10 -> -200
A14: Résultat avant impôt | B14: =B11+B13 -> 770.2 | C14: =C11+C13 -> 1827.4125 | D14: =D11+D13 -> 2953.5
A15: Impôt sur les sociétés | B15: =MAX(B14,0)*'01_Hypotheses_Scenarios'!B11 -> 192.55 | C15: =MAX(C14,0)*'01_Hypotheses_Scenarios'!C11 -> 456.85312 | D15: =MAX(D14,0)*'01_Hypotheses_Scenarios'!D11 -> 738.375
A16: Résultat net | B16: =B14-B15 -> 577.65 | C16: =C14-C15 -> 1370.5594 | D16: =D14-D15 -> 2215.125
A18: Capacité d'autofinancement (CAF = Résultat net + Amortissements) | B18: =B16+B9 -> 2852.675 | C18: =C16+C9 -> 3657.9094 | D18: =D16+D9 -> 4467.625
A19: Trésorerie N (réalisée, Étape 1) | B19: 2100 | C19: 2100 | D19: 2100
A20: Investissements estimés | B20: ='01_Hypotheses_Scenarios'!B12 -> 2500 | C20: ='01_Hypotheses_Scenarios'!C12 -> 2500 | D20: ='01_Hypotheses_Scenarios'!D12 -> 2500
A21: Variation du BFR estimée | B21: ='01_Hypotheses_Scenarios'!B13 -> 800 | C21: ='01_Hypotheses_Scenarios'!C13 -> 500 | D21: ='01_Hypotheses_Scenarios'!D13 -> 200
A22: Trésorerie estimée N+1 | B22: =B19+B18-B20-B21 -> 1652.675 | C22: =C19+C18-C20-C21 -> 2757.9094 | D22: =D19+D18-D20-D21 -> 3867.625

Sheet 03_Sensibilite
A1: ANALYSE DE SENSIBILITÉ - SCÉNARIO CENTRAL (base : Résultat d'exploitation N+1)
A3: Hypothèse testée (variation) | B3: Impact sur le résultat N+1 | C3: Commentaire
A4: Résultat d'exploitation central (référence) | B4: ='02_Previsions_N1'!C11 -> 2067.4125
A5: Volume d'activité +1 pt (avec coûts variables associés, ~40% de coûts variables) | B5: ='02_Previsions_N1'!C4*0.01*0.6 -> 263.925 | C5: Un point de volume supplémentaire ne se traduit pas intégralement en résultat : une partie des coûts (achats, personnel soignant) suit le volume
A6: Prix moyen +1 pt (à volume constant, sans effet coût) | B6: ='02_Previsions_N1'!C4*0.01 -> 439.875 | C6: Effet plein sur le résultat car aucun coût variable n'est associé à un effet prix pur
A7: Masse salariale / CA +1 pt (dérive non maîtrisée) | B7: -439.875 | C7: Effet symétrique au prix : chaque point de charge de personnel supplémentaire ampute le résultat d'autant
A8: Coût des achats / CA +1 pt | B8: -439.875 | C8: Sensibilité identique à la masse salariale : à surveiller notamment sur le bloc opératoire et le laboratoire (Étape 2)
A9: Productivité +1 pt (baisse de 1% des coûts totaux à activité constante) | B9: 419.20087 | C9: Un gain de productivité (ex. réduction du turnover, automatisation laboratoire) a un effet direct et non dilué sur le résultat
