Workbook

Sheet 00_Sommaire
A1: ÉTAPE 1 - DIAGNOSTIC FINANCIER - CHHS
A3: Centre hospitalier horizon SANTÉ (CHHS)
A4: Données fictives construites à des fins pédagogiques et professionnelles.
A6: Onglet | B6: Contenu
A7: 01_Compte_Resultat | B7: Compte de résultat simplifié N-2 / N-1 / N, évolutions et taux de marge
A8: 02_Bilan | B8: Bilan simplifié N-2 / N-1 / N (actif / passif) et contrôle d'équilibre
A9: 03_Ratios | B9: Tableau de ratios financiers (structure, liquidité, rentabilité) avec interprétation
A11: Convention de couleur
A12: Bleu = donnée saisie (hypothèse / donnée fictive source)
A13: Noir = formule calculée automatiquement
A14: Toute modification d'une donnée bleue se répercute automatiquement sur les calculs et les ratios.

Sheet 01_Compte_Resultat
A1: COMPTE DE RÉSULTAT SIMPLIFIÉ - CHHS (en k€)
A3: Poste | B3: N-2 | C3: N-1 | D3: N | E3: Évol. N-1/N-2 | F3: Évol. N/N-1
A4: Chiffre d'affaires | B4: 38000 | C4: 40200 | D4: 42500 | E4: =IFERROR(C4/B4-1,"-") -> 0.057894737 | F4: =IFERROR(D4/C4-1,"-") -> 0.05721393
A5: Achats consommés (médicaments, DM, consommables) | B5: 5700 | C5: 6110 | D5: 6588 | E5: =IFERROR(C5/B5-1,"-") -> 0.071929825 | F5: =IFERROR(D5/C5-1,"-") -> 0.078232406
A6: Charges externes (sous-traitance, locations, entretien, honoraires) | B6: 4560 | C6: 4744 | D6: 4888 | E6: =IFERROR(C6/B6-1,"-") -> 0.040350877 | F6: =IFERROR(D6/C6-1,"-") -> 0.030354132
A7: Charges de personnel | B7: 22420 | C7: 24120 | D7: 26138 | E7: =IFERROR(C7/B7-1,"-") -> 0.075825156 | F7: =IFERROR(D7/C7-1,"-") -> 0.083665008
A8: Impôts et taxes | B8: 760 | C8: 804 | D8: 850 | E8: =IFERROR(C8/B8-1,"-") -> 0.057894737 | F8: =IFERROR(D8/C8-1,"-") -> 0.05721393
A9: Dotations aux amortissements | B9: 1900 | C9: 2010 | D9: 2210 | E9: =IFERROR(C9/B9-1,"-") -> 0.057894737 | F9: =IFERROR(D9/C9-1,"-") -> 0.099502488
A10: Total charges d'exploitation | B10: =SUM(B5:B9) -> 35340 | C10: =SUM(C5:C9) -> 37788 | D10: =SUM(D5:D9) -> 40674 | E10: =IFERROR(C10/B10-1,"-") -> 0.069269949 | F10: =IFERROR(D10/C10-1,"-") -> 0.076373452
A11: Résultat d'exploitation | B11: =B4-B10 -> 2660 | C11: =C4-C10 -> 2412 | D11: =D4-D10 -> 1826 | E11: =IFERROR(C11/B11-1,"-") -> -0.093233083 | F11: =IFERROR(D11/C11-1,"-") -> -0.24295191
A12: Taux de marge d'exploitation (Résultat expl. / CA) | B12: =B11/B4 -> 0.07 | C12: =C11/C4 -> 0.06 | D12: =D11/D4 -> 0.042964706
A13: Résultat financier | B13: -150 | C13: -180 | D13: -220
A14: Résultat courant avant impôt | B14: =B11+B13 -> 2510 | C14: =C11+C13 -> 2232 | D14: =D11+D13 -> 1606
A15: Résultat exceptionnel | B15: 50 | C15: -30 | D15: 20
A16: Résultat avant impôt | B16: =B14+B15 -> 2560 | C16: =C14+C15 -> 2202 | D16: =D14+D15 -> 1626
A17: Taux d'impôt sur les sociétés (hypothèse) | B17: 0.25 | C17: 0.25 | D17: 0.25
A18: Impôt sur les sociétés | B18: =MAX(B16,0)*B17 -> 640 | C18: =MAX(C16,0)*C17 -> 550.5 | D18: =MAX(D16,0)*D17 -> 406.5
A19: Résultat net | B19: =B16-B18 -> 1920 | C19: =C16-C18 -> 1651.5 | D19: =D16-D18 -> 1219.5 | E19: =IFERROR(C19/B19-1,"-") -> -0.13984375 | F19: =IFERROR(D19/C19-1,"-") -> -0.26158038
A20: Taux de rentabilité nette (Résultat net / CA) | B20: =B19/B4 -> 0.050526316 | C20: =C19/C4 -> 0.04108209 | D20: =D19/D4 -> 0.028694118
A22: Note : modèle simplifié à but pédagogique - les postes ne détaillent pas l'ensemble du plan comptable général.

Sheet 02_Bilan
A1: BILAN SIMPLIFIÉ - CHHS (en k€)
A3: Poste | B3: N-2 | C3: N-1 | D3: N
A4: ACTIF
A5: Immobilisations nettes | B5: 18000 | C5: 19500 | D5: 21200
A6: Stocks (médicaments, consommables) | B6: 900 | C6: 950 | D6: 1050
A7: Créances clients | B7: 4685 | C7: 4955 | D7: 5240
A8: Trésorerie active | B8: 4200 | C8: 3400 | D8: 2100
A9: TOTAL ACTIF | B9: =SUM(B5:B8) -> 27785 | C9: =SUM(C5:C8) -> 28805 | D9: =SUM(D5:D8) -> 29590
A11: PASSIF
A12: Capitaux propres | B12: 14000 | C12: 15200 | D12: 16000
A13: Dettes financières (LT) | B13: 8000 | C13: 8800 | D13: 9900
A14: Dettes fournisseurs | B14: 937 | C14: 1004 | D14: 1083
A15: Autres dettes court terme (fiscal, social, divers) | B15: 4848 | C15: 3801 | D15: 2607
A16: TOTAL PASSIF | B16: =SUM(B12:B15) -> 27785 | C16: =SUM(C12:C15) -> 28805 | D16: =SUM(D12:D15) -> 29590
A18: Contrôle d'équilibre (Actif - Passif) | B18: =B9-B16 -> 0 | C18: =C9-C16 -> 0 | D18: =D9-D16 -> 0

Sheet 03_Ratios
A1: TABLEAU DE RATIOS FINANCIERS - CHHS
A3: Ratio | B3: Formule | C3: N-2 | D3: N-1 | E3: N | F3: Interprétation
A4: Taux de marge d'exploitation | B4: Résultat d'exploitation / CA | C4: ='01_Compte_Resultat'!B11/'01_Compte_Resultat'!B4 -> 0.07 | D4: ='01_Compte_Resultat'!C11/'01_Compte_Resultat'!C4 -> 0.06 | E4: ='01_Compte_Resultat'!D11/'01_Compte_Resultat'!D4 -> 0.042964706 | F4: Mesure la rentabilité opérationnelle avant éléments financiers et exceptionnels.
A5: Taux de rentabilité nette | B5: Résultat net / CA | C5: ='01_Compte_Resultat'!B19/'01_Compte_Resultat'!B4 -> 0.050526316 | D5: ='01_Compte_Resultat'!C19/'01_Compte_Resultat'!C4 -> 0.04108209 | E5: ='01_Compte_Resultat'!D19/'01_Compte_Resultat'!D4 -> 0.028694118 | F5: Mesure la rentabilité finale après charges financières, exceptionnelles et impôt.
A6: Poids des charges de personnel | B6: Charges de personnel / CA | C6: ='01_Compte_Resultat'!B7/'01_Compte_Resultat'!B4 -> 0.59 | D6: ='01_Compte_Resultat'!C7/'01_Compte_Resultat'!C4 -> 0.6 | E6: ='01_Compte_Resultat'!D7/'01_Compte_Resultat'!D4 -> 0.61501176 | F6: Suit la principale composante de coût du secteur de la santé.
A7: Poids des charges externes | B7: Charges externes / CA | C7: ='01_Compte_Resultat'!B6/'01_Compte_Resultat'!B4 -> 0.12 | D7: ='01_Compte_Resultat'!C6/'01_Compte_Resultat'!C4 -> 0.11800995 | E7: ='01_Compte_Resultat'!D6/'01_Compte_Resultat'!D4 -> 0.11501176 | F7: Suit le poids de la sous-traitance, des locations et des prestations externes.
A8: Fonds de roulement (FR) | B8: (Capitaux propres + Dettes financières LT) - Immobilisations nettes | C8: =('02_Bilan'!B12+'02_Bilan'!B13)-'02_Bilan'!B5 -> 4000 | D8: =('02_Bilan'!C12+'02_Bilan'!C13)-'02_Bilan'!C5 -> 4500 | E8: =('02_Bilan'!D12+'02_Bilan'!D13)-'02_Bilan'!D5 -> 4700 | F8: Ressources stables disponibles après financement des immobilisations.
A9: Besoin en fonds de roulement (BFR) | B9: (Stocks + Créances) - (Dettes fournisseurs + Autres dettes CT) | C9: =('02_Bilan'!B6+'02_Bilan'!B7)-('02_Bilan'!B14+'02_Bilan'!B15) -> -200 | D9: =('02_Bilan'!C6+'02_Bilan'!C7)-('02_Bilan'!C14+'02_Bilan'!C15) -> 1100 | E9: =('02_Bilan'!D6+'02_Bilan'!D7)-('02_Bilan'!D14+'02_Bilan'!D15) -> 2600 | F9: Besoin de financement lié au cycle d'exploitation.
A10: Trésorerie nette | B10: FR - BFR | C10: =C8-C9 -> 4200 | D10: =D8-D9 -> 3400 | E10: =E8-E9 -> 2100 | F10: Doit être cohérente avec la trésorerie active du bilan (contrôle de cohérence).
A11: Autonomie financière | B11: Capitaux propres / Total actif | C11: ='02_Bilan'!B12/'02_Bilan'!B9 -> 0.50386899 | D11: ='02_Bilan'!C12/'02_Bilan'!C9 -> 0.52768617 | E11: ='02_Bilan'!D12/'02_Bilan'!D9 -> 0.54072322 | F11: Part des ressources propres dans le financement total : plus le taux est élevé, plus la structure financière est solide.
A12: Taux d'endettement | B12: Dettes financières / Capitaux propres | C12: ='02_Bilan'!B13/'02_Bilan'!B12 -> 0.57142857 | D12: ='02_Bilan'!C13/'02_Bilan'!C12 -> 0.57894737 | E12: ='02_Bilan'!D13/'02_Bilan'!D12 -> 0.61875 | F12: Mesure le recours à l'endettement par rapport aux fonds propres.
A13: Liquidité générale | B13: (Stocks+Créances+Trésorerie) / (Dettes fournisseurs+Autres dettes CT) | C13: =('02_Bilan'!B6+'02_Bilan'!B7+'02_Bilan'!B8)/('02_Bilan'!B14+'02_Bilan'!B15) -> 1.6914434 | D13: =('02_Bilan'!C6+'02_Bilan'!C7+'02_Bilan'!C8)/('02_Bilan'!C14+'02_Bilan'!C15) -> 1.9365245 | E13: =('02_Bilan'!D6+'02_Bilan'!D7+'02_Bilan'!D8)/('02_Bilan'!D14+'02_Bilan'!D15) -> 2.2737127 | F13: Capacité à couvrir les dettes à court terme avec l'actif circulant.
