Workbook

Sheet 00_Sommaire
A1: ÉTAPE 3 - BUDGET ET ANALYSE DES ÉCARTS - CHHS
A3: Centre hospitalier horizon SANTÉ (CHHS) - Exercice N, Budget vs Réalisé
A4: Données fictives construites à des fins pédagogiques et professionnelles.
A6: Onglet | B6: Contenu
A7: 01_Budget_vs_Reel | B7: Comparaison Budget / Réalisé par activité (CA, coût, marge, volume, coût unitaire) avec seuils d'alerte
A8: 02_Decomposition_Ecarts | B8: Décomposition des écarts de CA (effet volume / effet prix) et de coût (effet volume / effet coût unitaire)
A9: Seuils d'alerte (appliqués sur les écarts en %)
A10: Vert | B10: Écart absolu < 5 %
A11: Orange | B11: Écart absolu entre 5 % et 10 %
A12: Rouge | B12: Écart absolu ≥ 10 %
A14: Les données réalisées reprennent strictement les volumes, CA et coûts par activité de l'Étape 2 (source unique de données).

Sheet 01_Budget_vs_Reel
A1: BUDGET vs RÉALISÉ PAR ACTIVITÉ - CHHS - EXERCICE N (en k€ sauf mention contraire)
A3: Activité | B3: CA Budget | C3: CA Réel | D3: Écart CA (k€) | E3: Écart CA (%) | F3: Coût Budget | G3: Coût Réel | H3: Écart Coût (k€) | I3: Écart Coût (%) | J3: Marge Budget | K3: Marge Réel | L3: Écart Marge (k€) | M3: Écart Marge (%) | N3: Coût unit. Budget (€) | O3: Coût unit. Réel (€) | P3: Écart coût unit. (%)
A4: Consultations externes | B4: =Q4*R4/1000 -> 6232 | C4: =U4 -> 6375 | D4: =C4-B4 -> 143 | E4: =IFERROR(D4/B4,"-") -> 0.022946085 | F4: =Q4*S4/1000 -> 4920 | G4: =V4 -> 5151.42 | H4: =G4-F4 -> 231.42 | I4: =IFERROR(H4/F4,"-") -> 0.047036585 | J4: =B4-F4 -> 1312 | K4: =C4-G4 -> 1223.58 | L4: =K4-J4 -> -88.42 | M4: =IFERROR(L4/ABS(J4),"-") -> -0.067393293 | N4: =S4 -> 60 | O4: =IFERROR(V4*1000/T4,"-") -> 60.604941 | P4: =IFERROR((O4-N4)/N4,"-") -> 0.010082353 | Q4: 82000 | R4: 76 | S4: 60 | T4: 85000 | U4: 6375 | V4: 5151.42
A5: Hospitalisation complète | B5: =Q5*R5/1000 -> 16985 | C5: =U5 -> 17000 | D5: =C5-B5 -> 15 | E5: =IFERROR(D5/B5,"-") -> 0.00088313218 | F5: =Q5*S5/1000 -> 15050 | G5: =V5 -> 15186.48 | H5: =G5-F5 -> 136.48 | I5: =IFERROR(H5/F5,"-") -> 0.0090684385 | J5: =B5-F5 -> 1935 | K5: =C5-G5 -> 1813.52 | L5: =K5-J5 -> -121.48 | M5: =IFERROR(L5/ABS(J5),"-") -> -0.062780362 | N5: =S5 -> 3500 | O5: =IFERROR(V5*1000/T5,"-") -> 3615.8286 | P5: =IFERROR((O5-N5)/N5,"-") -> 0.033093878 | Q5: 4300 | R5: 3950 | S5: 3500 | T5: 4200 | U5: 17000 | V5: 15186.48
A6: Hospitalisation de jour | B6: =Q6*R6/1000 -> 4940 | C6: =U6 -> 5100 | D6: =C6-B6 -> 160 | E6: =IFERROR(D6/B6,"-") -> 0.032388664 | F6: =Q6*S6/1000 -> 3640 | G6: =V6 -> 3987.84 | H6: =G6-F6 -> 347.84 | I6: =IFERROR(H6/F6,"-") -> 0.09556044 | J6: =B6-F6 -> 1300 | K6: =C6-G6 -> 1112.16 | L6: =K6-J6 -> -187.84 | M6: =IFERROR(L6/ABS(J6),"-") -> -0.14449231 | N6: =S6 -> 560 | O6: =IFERROR(V6*1000/T6,"-") -> 586.44706 | P6: =IFERROR((O6-N6)/N6,"-") -> 0.047226891 | Q6: 6500 | R6: 760 | S6: 560 | T6: 6800 | U6: 5100 | V6: 3987.84
A7: Bloc opératoire | B7: =Q7*R7/1000 -> 8500 | C7: =U7 -> 7650 | D7: =C7-B7 -> -850 | E7: =IFERROR(D7/B7,"-") -> -0.1 | F7: =Q7*S7/1000 -> 9860 | G7: =V7 -> 9910.8 | H7: =G7-F7 -> 50.8 | I7: =IFERROR(H7/F7,"-") -> 0.0051521298 | J7: =B7-F7 -> -1360 | K7: =C7-G7 -> -2260.8 | L7: =K7-J7 -> -900.8 | M7: =IFERROR(L7/ABS(J7),"-") -> -0.66235294 | N7: =S7 -> 2900 | O7: =IFERROR(V7*1000/T7,"-") -> 3197.0323 | P7: =IFERROR((O7-N7)/N7,"-") -> 0.10242492 | Q7: 3400 | R7: 2500 | S7: 2900 | T7: 3100 | U7: 7650 | V7: 9910.8
A8: Imagerie médicale | B8: =Q8*R8/1000 -> 4095 | C8: =U8 -> 4250 | D8: =C8-B8 -> 155 | E8: =IFERROR(D8/B8,"-") -> 0.037851038 | F8: =Q8*S8/1000 -> 3360 | G8: =V8 -> 3612.36 | H8: =G8-F8 -> 252.36 | I8: =IFERROR(H8/F8,"-") -> 0.075107143 | J8: =B8-F8 -> 735 | K8: =C8-G8 -> 637.64 | L8: =K8-J8 -> -97.36 | M8: =IFERROR(L8/ABS(J8),"-") -> -0.13246259 | N8: =S8 -> 160 | O8: =IFERROR(V8*1000/T8,"-") -> 164.19818 | P8: =IFERROR((O8-N8)/N8,"-") -> 0.026238636 | Q8: 21000 | R8: 195 | S8: 160 | T8: 22000 | U8: 4250 | V8: 3612.36
A9: Laboratoire | B9: =Q9*R9/1000 -> 2070 | C9: =U9 -> 2125 | D9: =C9-B9 -> 55 | E9: =IFERROR(D9/B9,"-") -> 0.026570048 | F9: =Q9*S9/1000 -> 2430 | G9: =V9 -> 2825.1 | H9: =G9-F9 -> 395.1 | I9: =IFERROR(H9/F9,"-") -> 0.16259259 | J9: =B9-F9 -> -360 | K9: =C9-G9 -> -700.1 | L9: =K9-J9 -> -340.1 | M9: =IFERROR(L9/ABS(J9),"-") -> -0.94472222 | N9: =S9 -> 27 | O9: =IFERROR(V9*1000/T9,"-") -> 29.737895 | P9: =IFERROR((O9-N9)/N9,"-") -> 0.10140351 | Q9: 90000 | R9: 23 | S9: 27 | T9: 95000 | U9: 2125 | V9: 2825.1
A10: TOTAL CHHS | B10: =SUM(B4:B9) -> 42822 | C10: =SUM(C4:C9) -> 42500 | D10: =SUM(D4:D9) -> -322 | E10: =D10/B10 -> -0.0075194993 | F10: =SUM(F4:F9) -> 39260 | G10: =SUM(G4:G9) -> 40674 | H10: =SUM(H4:H9) -> 1414 | I10: =H10/F10 -> 0.036016302 | J10: =SUM(J4:J9) -> 3562 | K10: =SUM(K4:K9) -> 1826 | L10: =SUM(L4:L9) -> -1736 | M10: =L10/ABS(J10) -> -0.48736665

Sheet 02_Decomposition_Ecarts
A1: DÉCOMPOSITION DES ÉCARTS - CA (VOLUME / PRIX) ET COÛT (VOLUME / COÛT UNITAIRE)
A3: ÉCART DE CHIFFRE D'AFFAIRES
A5: Activité | B5: Effet Volume (k€) | C5: Effet Prix (k€) | D5: Écart CA total (k€)
A6: Consultations externes | B6: =('01_Budget_vs_Reel'!T4-'01_Budget_vs_Reel'!Q4)*'01_Budget_vs_Reel'!R4/1000 -> 228 | C6: =(('01_Budget_vs_Reel'!U4*1000/'01_Budget_vs_Reel'!T4)-'01_Budget_vs_Reel'!R4)*'01_Budget_vs_Reel'!T4/1000 -> -85 | D6: =B6+C6 -> 143
A7: Hospitalisation complète | B7: =('01_Budget_vs_Reel'!T5-'01_Budget_vs_Reel'!Q5)*'01_Budget_vs_Reel'!R5/1000 -> -395 | C7: =(('01_Budget_vs_Reel'!U5*1000/'01_Budget_vs_Reel'!T5)-'01_Budget_vs_Reel'!R5)*'01_Budget_vs_Reel'!T5/1000 -> 410 | D7: =B7+C7 -> 15
A8: Hospitalisation de jour | B8: =('01_Budget_vs_Reel'!T6-'01_Budget_vs_Reel'!Q6)*'01_Budget_vs_Reel'!R6/1000 -> 228 | C8: =(('01_Budget_vs_Reel'!U6*1000/'01_Budget_vs_Reel'!T6)-'01_Budget_vs_Reel'!R6)*'01_Budget_vs_Reel'!T6/1000 -> -68 | D8: =B8+C8 -> 160
A9: Bloc opératoire | B9: =('01_Budget_vs_Reel'!T7-'01_Budget_vs_Reel'!Q7)*'01_Budget_vs_Reel'!R7/1000 -> -750 | C9: =(('01_Budget_vs_Reel'!U7*1000/'01_Budget_vs_Reel'!T7)-'01_Budget_vs_Reel'!R7)*'01_Budget_vs_Reel'!T7/1000 -> -100 | D9: =B9+C9 -> -850
A10: Imagerie médicale | B10: =('01_Budget_vs_Reel'!T8-'01_Budget_vs_Reel'!Q8)*'01_Budget_vs_Reel'!R8/1000 -> 195 | C10: =(('01_Budget_vs_Reel'!U8*1000/'01_Budget_vs_Reel'!T8)-'01_Budget_vs_Reel'!R8)*'01_Budget_vs_Reel'!T8/1000 -> -40 | D10: =B10+C10 -> 155
A11: Laboratoire | B11: =('01_Budget_vs_Reel'!T9-'01_Budget_vs_Reel'!Q9)*'01_Budget_vs_Reel'!R9/1000 -> 115 | C11: =(('01_Budget_vs_Reel'!U9*1000/'01_Budget_vs_Reel'!T9)-'01_Budget_vs_Reel'!R9)*'01_Budget_vs_Reel'!T9/1000 -> -60 | D11: =B11+C11 -> 55
A12: TOTAL | B12: =SUM(B6:B11) -> -379 | C12: =SUM(C6:C11) -> 57 | D12: =SUM(D6:D11) -> -322
A14: ÉCART DE COÛT
A15: Activité | B15: Effet Volume (k€) | C15: Effet Coût unitaire (k€) | D15: Écart Coût total (k€)
A16: Consultations externes | B16: ='01_Budget_vs_Reel'!S4*('01_Budget_vs_Reel'!T4-'01_Budget_vs_Reel'!Q4)/1000 -> 180 | C16: =(('01_Budget_vs_Reel'!V4*1000/'01_Budget_vs_Reel'!T4)-'01_Budget_vs_Reel'!S4)*'01_Budget_vs_Reel'!T4/1000 -> 51.42 | D16: =B16+C16 -> 231.42
A17: Hospitalisation complète | B17: ='01_Budget_vs_Reel'!S5*('01_Budget_vs_Reel'!T5-'01_Budget_vs_Reel'!Q5)/1000 -> -350 | C17: =(('01_Budget_vs_Reel'!V5*1000/'01_Budget_vs_Reel'!T5)-'01_Budget_vs_Reel'!S5)*'01_Budget_vs_Reel'!T5/1000 -> 486.48 | D17: =B17+C17 -> 136.48
A18: Hospitalisation de jour | B18: ='01_Budget_vs_Reel'!S6*('01_Budget_vs_Reel'!T6-'01_Budget_vs_Reel'!Q6)/1000 -> 168 | C18: =(('01_Budget_vs_Reel'!V6*1000/'01_Budget_vs_Reel'!T6)-'01_Budget_vs_Reel'!S6)*'01_Budget_vs_Reel'!T6/1000 -> 179.84 | D18: =B18+C18 -> 347.84
A19: Bloc opératoire | B19: ='01_Budget_vs_Reel'!S7*('01_Budget_vs_Reel'!T7-'01_Budget_vs_Reel'!Q7)/1000 -> -870 | C19: =(('01_Budget_vs_Reel'!V7*1000/'01_Budget_vs_Reel'!T7)-'01_Budget_vs_Reel'!S7)*'01_Budget_vs_Reel'!T7/1000 -> 920.8 | D19: =B19+C19 -> 50.8
A20: Imagerie médicale | B20: ='01_Budget_vs_Reel'!S8*('01_Budget_vs_Reel'!T8-'01_Budget_vs_Reel'!Q8)/1000 -> 160 | C20: =(('01_Budget_vs_Reel'!V8*1000/'01_Budget_vs_Reel'!T8)-'01_Budget_vs_Reel'!S8)*'01_Budget_vs_Reel'!T8/1000 -> 92.36 | D20: =B20+C20 -> 252.36
A21: Laboratoire | B21: ='01_Budget_vs_Reel'!S9*('01_Budget_vs_Reel'!T9-'01_Budget_vs_Reel'!Q9)/1000 -> 135 | C21: =(('01_Budget_vs_Reel'!V9*1000/'01_Budget_vs_Reel'!T9)-'01_Budget_vs_Reel'!S9)*'01_Budget_vs_Reel'!T9/1000 -> 260.1 | D21: =B21+C21 -> 395.1
A22: TOTAL | B22: =SUM(B16:B21) -> -577 | C22: =SUM(C16:C21) -> 1991 | D22: =SUM(D16:D21) -> 1414
A24: Lecture : un effet volume positif reflète une activité supérieure au budget (favorable en CA, mécaniquement défavorable en coût) ; un effet coût unitaire positif signale une dérive du coût par acte/séjour au-delà de l'hypothèse budgétaire.
